libsa4py/__init__.py
libsa4py/__main__.py
libsa4py/cst_extractor.py
libsa4py/cst_lenient_parser.py
libsa4py/cst_pipeline.py
libsa4py/cst_transformers.py
libsa4py/cst_visitor.py
libsa4py/exceptions.py
libsa4py/helper.py
libsa4py/merge.py
libsa4py/nl_preprocessing.py
libsa4py/pyre.py
libsa4py/representations.py
libsa4py/type_check.py
libsa4py/utils.py
libsa4py-0.4.0.dist-info/LICENSE
libsa4py-0.4.0.dist-info/METADATA
libsa4py-0.4.0.dist-info/WHEEL
libsa4py-0.4.0.dist-info/entry_points.txt
libsa4py-0.4.0.dist-info/top_level.txt
libsa4py-0.4.0.dist-info/RECORD
