Metadata-Version: 2.1
Name: libsa4py
Version: 0.4.0
Summary: LibSA4Py: Light-weight static analysis for extracting type hints and features
Home-page: https://github.com/saltudelft/libsa4py
Author: Amir M. Mir (TU Delft)
Author-email: mir-am@hotmail.com
Keywords: libsa4py static analysis features type hints type inference machine learning python pipeline light-weight
Classifier: License :: OSI Approved :: Apache Software License
Classifier: Environment :: Console
Classifier: Programming Language :: Python
Classifier: Programming Language :: Python :: 3.7
Classifier: Programming Language :: Python :: 3.8
Classifier: Programming Language :: Python :: 3.9
Classifier: Operating System :: Unix
Classifier: Intended Audience :: Science/Research
Classifier: Topic :: Scientific/Engineering :: Artificial Intelligence
Classifier: Topic :: Software Development :: Libraries :: Python Modules
License-File: LICENSE
Requires-Dist: libcst
Requires-Dist: numpy
Requires-Dist: pandas
Requires-Dist: nltk
Requires-Dist: joblib
Requires-Dist: tqdm
Requires-Dist: docstring-parser
Requires-Dist: dpu-utils
Requires-Dist: pyre-check
Requires-Dist: toml
Requires-Dist: mypy
